pymongo_voyageai_multimodal/__init__.py
pymongo_voyageai_multimodal/_version.py
pymongo_voyageai_multimodal/client.py
pymongo_voyageai_multimodal/document.py
pymongo_voyageai_multimodal/storage.py
pymongo_voyageai_multimodal/utils.py
pymongo_voyageai_multimodal-0.2.0.dist-info/METADATA
pymongo_voyageai_multimodal-0.2.0.dist-info/WHEEL
pymongo_voyageai_multimodal-0.2.0.dist-info/licenses/LICENSE
pymongo_voyageai_multimodal-0.2.0.dist-info/RECORD
