Metadata-Version: 2.4
Name: pymongo-voyageai-multimodal
Version: 0.2.0
Summary: PyMongo integration with VoyageAI for multimodal embedding
Project-URL: Download, https://github.com/mongodb-labs/pymongo-voyageai-multimodal/tags
Project-URL: Homepage, http://pymongo-voyageai-multimodal.readthedocs.org/
Author-email: Steve Silvester <steve.silvester@mongodb.com>
License:                                  Apache License
License-File: LICENSE
Classifier: Environment :: Web Environment
Classifier: Framework :: Flask
Classifier: Intended Audience :: Developers
Classifier: License :: OSI Approved :: BSD License
Classifier: Operating System :: OS Independent
Classifier: Programming Language :: Python :: 3.10
Classifier: Programming Language :: Python :: 3.11
Classifier: Programming Language :: Python :: 3.12
Classifier: Programming Language :: Python :: 3.13
Classifier: Programming Language :: Python :: Implementation :: CPython
Classifier: Programming Language :: Python :: Implementation :: PyPy
Classifier: Topic :: Internet :: WWW/HTTP :: Dynamic Content
Classifier: Topic :: Software Development :: Libraries :: Python Modules
Requires-Python: >=3.10
Requires-Dist: boto3>=1.37.25
Requires-Dist: certifi>=2025.4.26
Requires-Dist: langchain-mongodb>=0.6.0
Requires-Dist: pymongo>=4.12.0
Requires-Dist: voyageai>=0.3.0
